pyrodigy/__init__.py
pyrodigy/cli.py
pyrodigy/gan.py
pyrodigy/gansimple.ipynb
pyrodigy/optimizer_wrapper.py
pyrodigy-0.2.9.dist-info/LICENSE
pyrodigy-0.2.9.dist-info/METADATA
pyrodigy-0.2.9.dist-info/WHEEL
pyrodigy-0.2.9.dist-info/entry_points.txt
pyrodigy-0.2.9.dist-info/RECORD
