Metadata-Version: 2.1
Name: pyrodigy
Version: 0.2.9
Summary: No more excuses for bad models. >70 Optimizers. All explained. All pre-configured.
Home-page: https://github.com/pyros-sd-models/pyrodigy
License: Apache-2.0
Author: Pyro
Author-email: pyros.sd.models@gmail.com
Requires-Python: >=3.10,<4.0
Classifier: License :: OSI Approved :: Apache Software License
Classifier: Programming Language :: Python :: 3
Classifier: Programming Language :: Python :: 3.10
Classifier: Programming Language :: Python :: 3.11
Classifier: Programming Language :: Python :: 3.12
Requires-Dist: art (>=6.3,<7.0)
Requires-Dist: loguru
Requires-Dist: pytorch_optimizer
Requires-Dist: rich
Project-URL: Repository, https://github.com/pyros-sd-models/pyrodigy
